Metadata-Version: 2.4
Name: veomni
Version: 0.1.4
Summary: VeOmni: Scaling any Modality Model Training to any Accelerators with PyTorch native Training Framework
Author-email: Fazzie <maqianli.fazzie@bytedance.com>
License: 
Project-URL: Homepage, https://github.com/ByteDance-Seed/VeOmni
Project-URL: Source Code, https://github.com/ByteDance-Seed/VeOmni
Requires-Python: >=3.11
License-File: LICENSE
Requires-Dist: blobfile>=3.0.0
Requires-Dist: datasets<=2.21.0,>=2.16.0
Requires-Dist: packaging<26.0,>=23.0
Requires-Dist: torchdata<1.0,>=0.8.0
Requires-Dist: tiktoken>=0.9.0
Requires-Dist: diffusers<=0.31.0,>=0.30.0
Requires-Dist: transformers[torch]==4.57.3
Requires-Dist: psutil
Requires-Dist: timm
Requires-Dist: wandb
Provides-Extra: dev
Requires-Dist: pre-commit<5.0,>=4.0.0; extra == "dev"
Requires-Dist: ruff<1.0,>=0.7.0; extra == "dev"
Requires-Dist: pytest<8.0,>=6.0.0; extra == "dev"
Requires-Dist: expecttest<0.4,>=0.3.0; extra == "dev"
Provides-Extra: audio
Requires-Dist: av<15.0,>=14.3.0; extra == "audio"
Requires-Dist: librosa<0.12,>=0.11.0; extra == "audio"
Requires-Dist: soundfile<0.14,>=0.13.1; extra == "audio"
Provides-Extra: dit
Requires-Dist: diffusers<=0.31.0,>=0.30.0; extra == "dit"
Requires-Dist: bitsandbytes<=0.47.0,>=0.46.0; extra == "dit"
Provides-Extra: npu
Requires-Dist: torch==2.7.1+cpu; extra == "npu"
Requires-Dist: torch-npu==2.7.1; extra == "npu"
Requires-Dist: torchvision==0.22.1; platform_machine == "aarch64" and extra == "npu"
Requires-Dist: torchaudio==2.7.1; platform_machine == "aarch64" and extra == "npu"
Requires-Dist: torchvision==0.22.1+cpu; platform_machine != "aarch64" and extra == "npu"
Requires-Dist: torchaudio==2.7.1+cpu; platform_machine != "aarch64" and extra == "npu"
Requires-Dist: decorator>=5.2.1; extra == "npu"
Requires-Dist: einops>=0.8.1; extra == "npu"
Requires-Dist: scipy>=1.16.2; extra == "npu"
Provides-Extra: gpu
Requires-Dist: torch==2.8.0+cu128; extra == "gpu"
Requires-Dist: torchvision==0.23.0+cu128; extra == "gpu"
Requires-Dist: torchaudio==2.8.0+cu128; extra == "gpu"
Requires-Dist: liger-kernel; extra == "gpu"
Requires-Dist: flash-attn; extra == "gpu"
Provides-Extra: megatron
Requires-Dist: megatron-energon>=7.2.1; extra == "megatron"
Dynamic: license-file
